LICENSE
README.md
setup.py
carefree_toolkit.egg-info/PKG-INFO
carefree_toolkit.egg-info/SOURCES.txt
carefree_toolkit.egg-info/dependency_links.txt
carefree_toolkit.egg-info/requires.txt
carefree_toolkit.egg-info/top_level.txt
cftool/__init__.py
cftool/array.py
cftool/console.py
cftool/constants.py
cftool/cv.py
cftool/data_structures.py
cftool/geometry.py
cftool/manage.py
cftool/misc.py
cftool/pipeline.py
cftool/requests.py
cftool/types.py
cftool/web.py
cftool/dist/__init__.py
cftool/dist/core.py
cftool/noli/__init__.py
cftool/noli/api.py
cftool/noli/schema.py
cftool/noli/exporters/__init__.py
cftool/noli/exporters/image.py
tests/test_array.py
tests/test_misc.py
tests/test_parallel.py