Metadata-Version: 2.1
Name: carefree-toolkit
Version: 0.3.10
Summary: Some commonly used functions and modules
Home-page: https://github.com/carefree0910/carefree-toolkit
Download-URL: https://github.com/carefree0910/carefree-toolkit/archive/v0.3.10.tar.gz
Author: carefree0910
Author-email: syameimaru.saki@gmail.com
Keywords: python numpy data-science
License-File: LICENSE
